simple_repository/__init__.py
simple_repository/_frozen_json.py
simple_repository/_private_metadata.py
simple_repository/_typing_compat.py
simple_repository/_version.py
simple_repository/content_negotiation.py
simple_repository/errors.py
simple_repository/html_parser.py
simple_repository/model.py
simple_repository/packaging.py
simple_repository/parser.py
simple_repository/py.typed
simple_repository/serializer.py
simple_repository/utils.py
simple_repository/components/__init__.py
simple_repository/components/allow_list.py
simple_repository/components/core.py
simple_repository/components/deny_list.py
simple_repository/components/http.py
simple_repository/components/http_cached.py
simple_repository/components/local.py
simple_repository/components/merged.py
simple_repository/components/metadata_injector.py
simple_repository/components/new_releases_remover.py
simple_repository/components/priority_selected.py
simple_repository/components/private_metadata_setter.py
simple_repository/components/resource_cache.py
simple_repository/components/yanking.py
simple_repository/tests/__init__.py
simple_repository/tests/test__frozen_json.py
simple_repository/tests/test__private_metadata.py
simple_repository/tests/test_content_negotiation.py
simple_repository/tests/test_html_parser.py
simple_repository/tests/test_model.py
simple_repository/tests/test_packaging.py
simple_repository/tests/test_parser.py
simple_repository/tests/test_serializer.py
simple_repository/tests/test_simple_repository.py
simple_repository/tests/test_utils.py
simple_repository/tests/components/__init__.py
simple_repository/tests/components/conftest.py
simple_repository/tests/components/fake_repository.py
simple_repository/tests/components/mock_compat.py
simple_repository/tests/components/test_allow_list.py
simple_repository/tests/components/test_deny_list.py
simple_repository/tests/components/test_http_cached_repo.py
simple_repository/tests/components/test_http_repository.py
simple_repository-0.10.3.dist-info/licenses/LICENSE
simple_repository-0.10.3.dist-info/METADATA
simple_repository-0.10.3.dist-info/WHEEL
simple_repository-0.10.3.dist-info/top_level.txt
simple_repository-0.10.3.dist-info/RECORD
