Metadata-Version: 2.4
Name: simple-repository
Version: 0.10.3
Summary: The core simple repository (PEP-503) interface, including powerful component implementations suitable for use in repository clients and servers
Author: Phil Elson, Ivan Sinkarenko, Francesco Iannaccone, Wouter Koorn
Project-URL: Homepage, https://github.com/simple-repository/simple-repository
Classifier: Development Status :: 5 - Production/Stable
Classifier: Programming Language :: Python :: 3
Classifier: Operating System :: POSIX
Classifier: Typing :: Typed
Requires-Python: >=3.7
License-File: LICENSE
Requires-Dist: httpx
Requires-Dist: aiosqlite
Requires-Dist: packaging
Requires-Dist: typing_extensions>=4.4.0; python_version < "3.12"
Provides-Extra: test
Requires-Dist: pytest; extra == "test"
Requires-Dist: pytest_asyncio; extra == "test"
Requires-Dist: pytest_httpx; extra == "test"
Requires-Dist: mock~=5.0.2; python_version < "3.8" and extra == "test"
Provides-Extra: dev
Requires-Dist: simple-repository[test]; extra == "dev"
Dynamic: license-file
